licchart/__init__.py
licchart/app.py
licchart/helpers.py
licchart-0.1.4.dist-info/LICENSE
licchart-0.1.4.dist-info/METADATA
licchart-0.1.4.dist-info/WHEEL
licchart-0.1.4.dist-info/entry_points.txt
licchart-0.1.4.dist-info/top_level.txt
licchart-0.1.4.dist-info/RECORD
