Metadata-Version: 2.1
Name: licchart
Version: 0.1.4
Summary: A Last.fm Bar Chart Race Maker
Author-email: Stelvey <stelveflame@gmail.com>
License: GNU GPL v3
Project-URL: Homepage, https://github.com/Stelvey/LICCHART
Project-URL: Bug Tracker, https://github.com/Stelvey/LICCHART/issues
Classifier: Programming Language :: Python :: 3
Classifier: License :: OSI Approved :: GNU General Public License v3 (GPLv3)
Classifier: Operating System :: OS Independent
License-File: LICENSE
Requires-Dist: bar-chart-race
Requires-Dist: cutlet
Requires-Dist: regex
Requires-Dist: requests
Requires-Dist: unidic-lite
